Metadata-Version: 2.1
Name: wiselink
Version: 0.0.1
Summary: Wiselink
Author: MF
